mp4fixer/__init__.py
mp4fixer/fix.py
mp4fixer/fp
mp4fixer/mf
mp4fixer/mp4analyzer.py
mp4fixer-0.2.1.dist-info/METADATA
mp4fixer-0.2.1.dist-info/WHEEL
mp4fixer-0.2.1.dist-info/entry_points.txt
mp4fixer-0.2.1.dist-info/top_level.txt
mp4fixer-0.2.1.dist-info/RECORD
