Metadata-Version: 2.4
Name: mp4fixer
Version: 0.2.1
Summary: A powerful mp4 files fixer and analyzer that fix 70% to 90% of mp4 files
Home-page: https://pypi.org/project/mp4fixer
Author: Abdul Moeez
Requires-Python: >=3.7
Requires-Dist: argparse
Requires-Dist: colorama
Requires-Dist: lolpython
Requires-Dist: pyfiglet
Dynamic: author
Dynamic: description
Dynamic: description-content-type
Dynamic: home-page
Dynamic: requires-dist
Dynamic: requires-python
Dynamic: summary
